{"skeleton":{"hash":"nyqQO6BvpJI","spine":"4.1.17","x":-87.83,"y":0.00709,"width":319.30,"height":336.96,"images":"./images/","audio":""},"bones":[{"name":"root"},{"name":"hip","parent":"root","y":94.89},{"name":"body","parent":"hip","length":60.79,"x":4.09,"y":3.18,"rotation":96.39},{"name":"thigh1","parent":"hip","length":23.95,"x":-17.52,"y":-5.23,"rotation":-107.07},{"name":"shin1","parent":"thigh1","length":28.24,"x":29.77,"y":-0.91194,"rotation":10.27},{"name":"thigh2","parent":"hip","length":23.66,"x":21.86,"y":-5.87,"rotation":-85.46},{"name":"shin2","parent":"thigh2","length":25.35,"x":31.99,"y":2.97,"rotation":-2.25},{"name":"head","parent":"body","length":24.35,"x":74.55,"y":-4.84,"rotation":-92.69},{"name":"mantles","parent":"body","x":48.48,"y":-9.00,"rotation":-2.25},{"name":"upperarm1","parent":"body","length":19.36,"x":52.50,"y":41.85,"rotation":130.11},{"name":"upperarm2","parent":"body","length":25.99,"x":57.95,"y":-38.94,"rotation":-178.96},{"name":"foot1","parent":"shin1","length":27.08,"x":28.17,"y":-0.48516,"rotation":-90.96,"transform":"noRotationOrReflection"},{"name":"foot2","parent":"shin2","length":22.29,"x":25.55,"y":0.27842,"rotation":-90.42,"transform":"noRotationOrReflection"},{"name":"forearm1","parent":"upperarm1","length":22.06,"x":23.97,"y":5.16,"rotation":30.56},{"name":"forearm2","parent":"upperarm2","length":15.30,"x":28.74,"y":-0.90204,"rotation":6.80},{"name":"hand1","parent":"forearm1","length":28.01,"x":27.54,"y":0.44823,"rotation":16.24},{"name":"hand2","parent":"forearm2","length":23.77,"x":22.80,"y":-0.21814,"rotation":1.35},{"name":"weapon","parent":"hand2","length":157.40,"x":15.98,"y":1.43,"rotation":77.91}],"slots":[{"name":"upperarm2","bone":"upperarm2","attachment":"upper-arm2"},{"name":"sword","bone":"root"},{"name":"hand2","bone":"hand2","attachment":"hand2"},{"name":"weapon","bone":"weapon","attachment":"sword"},{"name":"fingers","bone":"hand2","attachment":"fingers"},{"name":"forearm2","bone":"forearm2","attachment":"forearm2"},{"name":"thigh2","bone":"thigh2","attachment":"thigh2"},{"name":"foot2","bone":"foot2","attachment":"foot2"},{"name":"shin2","bone":"shin2","attachment":"shin2"},{"name":"thigh1","bone":"thigh1","attachment":"thigh1"},{"name":"foot1","bone":"foot1","attachment":"foot1"},{"name":"body","bone":"body","attachment":"body"},{"name":"shin1","bone":"shin1","attachment":"shin1"},{"name":"upperarm1","bone":"upperarm1","attachment":"upper-arm1"},{"name":"mantles","bone":"mantles","attachment":"mantles"},{"name":"head","bone":"head","attachment":"head"},{"name":"mouth","bone":"head","attachment":"mouth"},{"name":"eyes","bone":"head","attachment":"eyes"},{"name":"forearm1","bone":"forearm1","attachment":"forearm1"},{"name":"hand1","bone":"hand1","attachment":"hand1"}],"skins":[{"name":"default","attachments":{"body":{"body":{"x":33.82,"y":2.60,"rotation":-92.70,"width":97,"height":95}},"eyes":{"eyes":{"x":6.48,"y":50.75,"rotation":0.12350,"width":82,"height":31}},"fingers":{"fingers":{"x":16.22,"y":1.37,"rotation":82.36,"width":31,"height":33}},"foot1":{"foot1":{"x":12.55,"y":0.12199,"rotation":90.96,"width":50,"height":42}},"foot2":{"foot2":{"x":8.83,"y":2.92,"rotation":90.42,"width":53,"height":38}},"forearm1":{"forearm1":{"x":11.88,"y":-5.04,"rotation":106.62,"width":41,"height":49}},"forearm2":{"forearm2":{"x":13.09,"y":-0.63903,"rotation":83.72,"width":31,"height":32}},"hand1":{"hand1":{"x":11.93,"y":-0.70330,"rotation":90.37,"width":37,"height":48}},"hand2":{"hand2":{"x":14.24,"y":1.64,"rotation":82.36,"width":31,"height":37}},"head":{"head":{"x":7.80,"y":71.88,"rotation":0.12350,"width":172,"height":173}},"mantles":{"mantles":{"x":15.58,"y":11.76,"rotation":-90.45,"width":136,"height":55}},"mouth":{"mouth":{"x":12.07,"y":10.76,"rotation":0.12350,"width":61,"height":13}},"shin1":{"shin1":{"x":8.96,"y":0.67213,"rotation":96.81,"width":53,"height":57}},"shin2":{"shin2":{"x":2.25,"y":-2.94,"rotation":87.72,"width":51,"height":54}},"thigh1":{"thigh1":{"x":11.99,"y":-1.02,"rotation":107.07,"width":60,"height":63}},"thigh2":{"thigh2":{"x":15.71,"y":-4.62,"rotation":85.46,"width":57,"height":64}},"upperarm1":{"upper-arm1":{"x":6.60,"y":0.05508,"rotation":137.18,"width":50,"height":56}},"upperarm2":{"upper-arm2":{"x":13.33,"y":-2.22,"rotation":90.45,"width":39,"height":59}},"weapon":{"sword":{"x":71.39,"y":0.20471,"rotation":0.19671,"width":216,"height":69}}}}],"events":{"footstep":{"string":""}},"animations":{"attack":{"bones":{"body":{"rotate":[{"value":2.20},{"time":0.06667,"value":13.22},{"time":0.13333,"value":-9.59},{"time":0.20000,"value":-23.59},{"time":0.26667,"value":-32.15},{"time":0.40000,"value":2.20}],"translate":[{"x":-0.76897,"y":-1.89},{"time":0.13333,"x":4.86,"y":-0.24301},{"time":0.20000,"x":8.05,"y":-2.44},{"time":0.40000,"x":-0.76897,"y":-1.89}]},"foot1":{"rotate":[{"value":8.90}]},"foot2":{"rotate":[{"value":-13.12}]},"forearm1":{"rotate":[{"value":7.94},{"time":0.06667,"value":42.31},{"time":0.13333,"value":21.87},{"time":0.33333,"value":43.27},{"time":0.40000,"value":7.94}]},"forearm2":{"rotate":[{"value":56.31},{"time":0.06667,"value":87.63},{"time":0.13333,"value":6.52},{"time":0.20000,"value":1.00},{"time":0.26667,"value":45.15},{"time":0.40000,"value":56.31}]},"hand1":{"rotate":[{},{"time":0.13333,"value":-8.94},{"time":0.26667,"value":-20.80},{"time":0.40000}]},"hand2":{"rotate":[{"value":17.89},{"time":0.06667,"value":-12.89},{"time":0.13333,"value":-11.39},{"time":0.20000,"value":6.20},{"time":0.26667,"value":18.97},{"time":0.40000,"value":17.89}]},"head":{"rotate":[{"value":-19.21},{"time":0.06667,"value":-19.17},{"time":0.13333,"value":4.77},{"time":0.20000,"value":12.47},{"time":0.26667,"value":12.58},{"time":0.40000,"value":-19.21}],"translate":[{},{"time":0.06667,"x":3.47,"y":5.70},{"time":0.20000,"x":-4.56,"y":-12.28},{"time":0.40000}]},"hip":{"translate":[{"x":-12.60,"y":-11.34},{"time":0.06667,"x":-20.76,"y":-23.09},{"time":0.13333,"x":-15.51,"y":-16.91},{"time":0.20000,"x":-5.89,"y":-21.85},{"time":0.26667,"x":-7.08,"y":-25.29},{"time":0.40000,"x":-12.60,"y":-11.34}]},"mantles":{"rotate":[{"value":-8.28},{"time":0.06667,"value":5.33},{"time":0.13333,"value":4.81},{"time":0.20000,"value":-2.43},{"time":0.26667,"value":-12.35},{"time":0.40000,"value":-8.28}],"translate":[{},{"time":0.06667,"x":5.51,"y":-5.45},{"time":0.13333,"x":1.54,"y":-5.87},{"time":0.20000,"x":0.46658,"y":-6.12},{"time":0.26667,"x":-6.55,"y":-4.72},{"time":0.40000}]},"shin1":{"rotate":[{"value":-48.68},{"time":0.06667,"value":-57.40},{"time":0.13333,"value":-59.24},{"time":0.20000,"value":-96.98},{"time":0.26667,"value":-101.31},{"time":0.33333,"value":-80.07},{"time":0.40000,"value":-48.68}]},"shin2":{"rotate":[{"value":-32.20},{"time":0.03333,"value":-58.22},{"time":0.06667,"value":-84.23},{"time":0.10000,"value":-69.96},{"time":0.13333,"value":-55.68},{"time":0.20000,"value":-34.60},{"time":0.26667,"value":-56.02},{"time":0.33333,"value":-49.51},{"time":0.40000,"value":-32.20}]},"thigh1":{"rotate":[{"value":78.20},{"time":0.06667,"value":97.48},{"time":0.13333,"value":89.67},{"time":0.20000,"value":104.07},{"time":0.26667,"value":110.65},{"time":0.33333,"value":96.43},{"time":0.40000,"value":78.20}],"translate":[{"x":14.51,"y":-3.79}]},"thigh2":{"rotate":[{"value":-21.79},{"time":0.03333,"value":-12.45},{"time":0.06667,"value":-3.11},{"time":0.10000,"value":-11.46},{"time":0.13333,"value":-19.82},{"time":0.20000,"value":-43.82},{"time":0.26667,"value":-33.61},{"time":0.33333,"value":-24.80},{"time":0.40000,"value":-21.79}],"translate":[{"x":-22.58,"y":1.52},{"time":0.20000,"x":-13.27,"y":-2.40},{"time":0.40000,"x":-22.58,"y":1.52}]},"upperarm1":{"rotate":[{"value":-4.05},{"time":0.06667,"value":33.65},{"time":0.13333,"value":-3.75},{"time":0.26667,"value":-49.65},{"time":0.33333,"value":-42.31},{"time":0.40000,"value":-4.05}],"translate":[{},{"time":0.20000,"x":-2.50,"y":-6.51},{"time":0.40000}]},"upperarm2":{"rotate":[{"value":324.47},{"time":0.06667,"value":461.05},{"time":0.13333,"value":409.06},{"time":0.20000,"value":375.11},{"time":0.26667,"value":313.18},{"time":0.40000,"value":324.47}],"translate":[{},{"time":0.13333,"x":-2.10,"y":-8.13},{"time":0.20000,"x":-10.56,"y":1.26},{"time":0.40000}]}}},"crouch":{"bones":{"body":{"rotate":[{"value":-15.51,"curve":[0.12500,-15.51,0.37500,-11.54]},{"time":0.50000,"value":-11.54,"curve":[0.62500,-11.54,0.87500,-15.51]},{"time":1,"value":-15.51}],"translate":[{"x":-0.41277,"y":-2.33,"curve":[0.12500,-0.41277,0.37500,-2.21,0.12500,-2.33,0.37500,-0.53446]},{"time":0.50000,"x":-2.21,"y":-0.53446,"curve":[0.62500,-2.21,0.87500,-0.41277,0.62500,-0.53446,0.87500,-2.33]},{"time":1,"x":-0.41277,"y":-2.33}]},"foot1":{"rotate":[{"value":270.13}]},"forearm1":{"rotate":[{"value":25.39},{"time":0.50000,"value":32.07},{"time":1,"value":25.39}]},"forearm2":{"rotate":[{"value":18.60},{"time":0.50000,"value":26.16},{"time":1,"value":18.60}]},"hand1":{"rotate":[{"value":-9.30},{"time":0.50000,"value":-1.97},{"time":1,"value":-9.30}]},"hand2":{"rotate":[{"value":-13.40},{"time":0.50000,"value":-17.29},{"time":1,"value":-13.40}]},"head":{"rotate":[{"value":8.73},{"time":0.50000,"value":3.25},{"time":1,"value":8.73}],"translate":[{"x":-4.43,"y":-2.86,"curve":[0.06032,-4.70,0.11629,-4.85,0.06032,-2.99,0.11629,-3.06]},{"time":0.16667,"x":-4.85,"y":-3.06,"curve":[0.29167,-4.85,0.54167,-2.36,0.29167,-3.06,0.54167,-1.86]},{"time":0.66667,"x":-2.36,"y":-1.86,"curve":[0.78667,-3.27,0.90051,-4.02,0.78667,-2.30,0.90051,-2.66]},{"time":1,"x":-4.43,"y":-2.86}]},"hip":{"translate":[{"x":-11.23,"y":-42.01}]},"mantles":{"rotate":[{"value":9.05},{"time":0.50000,"value":7.13},{"time":1,"value":9.05}],"translate":[{"x":-0.09852}]},"shin1":{"rotate":[{"value":-92.82}]},"shin2":{"rotate":[{"value":-80.65}]},"thigh1":{"rotate":[{"value":14.43}],"translate":[{"x":-0.92970,"y":6.68}]},"thigh2":{"rotate":[{"value":89.15}],"translate":[{"x":-2.75,"y":7.6E-06}]},"upperarm1":{"rotate":[{"value":-5.42},{"time":0.50000,"value":-11.10},{"time":1,"value":-5.42}],"translate":[{"x":-6.95,"y":5.86}]},"upperarm2":{"rotate":[{"value":38.04},{"time":0.50000,"value":30.80},{"time":1,"value":38.04}]}}},"fall":{"bones":{"body":{"rotate":[{"value":14.14}]},"foot1":{"rotate":[{"value":19.63}]},"foot2":{"rotate":[{"value":39.17}]},"forearm1":{"rotate":[{"value":26.18}]},"forearm2":{"rotate":[{"value":12.31}]},"head":{"rotate":[{"value":-17.81}]},"shin1":{"rotate":[{"value":-37.59}]},"shin2":{"rotate":[{"value":-39.70}]},"thigh1":{"rotate":[{"value":53.96}]},"thigh2":{"rotate":[{"value":32.44}]},"upperarm1":{"rotate":[{"value":-25.71}]},"upperarm2":{"rotate":[{"value":37.75}]},"weapon":{"translate":[{"time":1}]}}},"idle":{"bones":{"body":{"rotate":[{},{"time":0.50000,"value":1.67},{"time":1}],"translate":[{"curve":[0.12500,0,0.37500,0,0.12500,0,0.37500,-3.70]},{"time":0.50000,"y":-3.70,"curve":[0.62500,0,0.87500,0,0.62500,-3.70,0.87500,0]},{"time":1}]},"forearm1":{"rotate":[{"curve":[0.20217,-1.4E-44,0.37500,9.63]},{"time":0.50000,"value":9.63,"curve":[0.75844,9.63,0.87500,0]},{"time":1}]},"forearm2":{"rotate":[{},{"time":0.50000,"value":13.64},{"time":1}]},"hand1":{"rotate":[{"curve":[0.20217,-1.7E-44,0.37500,12.37]},{"time":0.50000,"value":12.37,"curve":[0.75844,12.37,0.87500,0]},{"time":1}]},"hand2":{"rotate":[{},{"time":0.50000,"value":-8.65},{"time":1}]},"head":{"rotate":[{"value":-4.18},{"time":0.50000,"value":-8.26},{"time":1,"value":-4.18}],"translate":[{"x":-1.06,"curve":[0.06373,-0.45597,0.12255,0,0.06373,0,0.12255,0]},{"time":0.16667,"curve":[0.29167,0,0.54167,-3.75,0.29167,0,0.54167,0]},{"time":0.66667,"x":-3.75,"curve":[0.74775,-3.75,0.88288,-2.14,0.74775,0,0.88288,0]},{"time":1,"x":-1.06}]},"hip":{"translate":[{"y":-2.92,"curve":[0.12500,0,0.37500,-3.18,0.12500,-2.92,0.37500,-4.04]},{"time":0.50000,"x":-3.18,"y":-4.04,"curve":[0.62500,-3.18,0.87500,0,0.62500,-4.04,0.87500,-2.92]},{"time":1,"y":-2.92}]},"mantles":{"rotate":[{},{"time":0.43333,"value":-4.84,"curve":[0.57500,-4.84,0.85833,0]},{"time":1}],"translate":[{"x":-0.09852,"curve":[0.13019,-0.37618,0.32758,-1.42,0.13019,0,0.32758,0]},{"time":0.43333,"x":-1.42,"curve":[0.55833,-1.42,0.80833,0,0.55833,0,0.80833,0]},{"time":0.93333},{"time":1,"x":-0.09852}]},"shin1":{"rotate":[{"value":-30.35},{"time":0.13333,"value":-35.18},{"time":0.23333,"value":-40.04},{"time":0.33333,"value":-44.23},{"time":0.43333,"value":-47.28},{"time":0.53333,"value":-47.90},{"time":0.63333,"value":-45.42},{"time":0.73333,"value":-41.53},{"time":0.83333,"value":-36.85},{"time":0.93333,"value":-32.14},{"time":1,"value":-30.35}]},"shin2":{"rotate":[{"value":-23.54},{"time":0.13333,"value":-24.09},{"time":0.23333,"value":-24.68},{"time":0.33333,"value":-25.18},{"time":0.43333,"value":-25.51},{"time":0.53333,"value":-25.57},{"time":0.63333,"value":-25.31},{"time":0.73333,"value":-24.86},{"time":0.83333,"value":-24.30},{"time":0.93333,"value":-23.74},{"time":1,"value":-23.54}]},"thigh1":{"rotate":[{"value":6.60},{"time":0.13333,"value":9.48},{"time":0.23333,"value":12.50},{"time":0.33333,"value":15.24},{"time":0.43333,"value":17.31},{"time":0.53333,"value":17.74},{"time":0.63333,"value":16.04},{"time":0.73333,"value":13.46},{"time":0.83333,"value":10.50},{"time":0.93333,"value":7.65},{"time":1,"value":6.60}]},"thigh2":{"rotate":[{"value":16.55},{"time":0.13333,"value":17.50},{"time":0.23333,"value":18.63},{"time":0.33333,"value":19.76},{"time":0.43333,"value":20.65},{"time":0.53333,"value":20.84},{"time":0.63333,"value":20.10},{"time":0.73333,"value":19.02},{"time":0.83333,"value":17.87},{"time":0.93333,"value":16.88},{"time":1,"value":16.55}]},"upperarm1":{"rotate":[{"curve":[0.20217,2.1E-44,0.37500,-15.40]},{"time":0.50000,"value":-15.40,"curve":[0.75844,-15.40,0.87500,0]},{"time":1}],"translate":[{"curve":[0.20217,-2.8E-45,0.37500,1.84,0.20217,7.0E-45,0.37500,-5.01]},{"time":0.50000,"x":1.84,"y":-5.01,"curve":[0.75844,1.84,0.87500,0,0.75844,-5.01,0.87500,0]},{"time":1}]},"upperarm2":{"rotate":[{"value":0.46172},{"time":0.50000,"value":-1.20},{"time":1,"value":0.46172}],"translate":[{},{"time":0.50000,"x":-3.13,"y":8.02},{"time":1}]}}},"jump":{"bones":{"body":{"rotate":[{"value":-10.40}]},"foot1":{"rotate":[{"value":-32.24}]},"foot2":{"rotate":[{"value":-33.31}]},"forearm1":{"rotate":[{"value":56.42}]},"forearm2":{"rotate":[{"value":20.06}]},"head":{"rotate":[{"value":4.89}]},"shin1":{"rotate":[{"value":-40.43}]},"shin2":{"rotate":[{"value":-70.32}]},"thigh1":{"rotate":[{"value":21.27}]},"thigh2":{"rotate":[{"value":22.92}]},"upperarm1":{"rotate":[{"value":22.69}]},"upperarm2":{"rotate":[{"value":23.72}]},"weapon":{"translate":[{"time":1}]}}},"run":{"bones":{"body":{"rotate":[{"value":-11.15},{"time":0.04407,"value":-16.76},{"time":0.17629,"value":-8.61},{"time":0.31171,"value":-20.18},{"time":0.44073,"value":-8.61},{"time":0.53333,"value":-11.15}],"translate":[{"x":3.37,"y":-2.53},{"time":0.04407,"x":4.99,"y":0.87499},{"time":0.17629,"x":2.61,"y":4.03},{"time":0.31171,"x":5.73,"y":0.46590},{"time":0.44073,"x":2.70,"y":5.11},{"time":0.53333,"x":3.37,"y":-2.53}]},"foot1":{"rotate":[{"value":20.27},{"time":0.04407,"value":-0.60803},{"time":0.13222,"value":-31.14},{"time":0.17629,"value":-97.65},{"time":0.22037,"value":-71.21},{"time":0.26667,"value":-84.96},{"time":0.31171,"value":-63.21},{"time":0.35259,"value":-8.37},{"time":0.39666,"value":-18.34},{"time":0.44073,"value":34.08},{"time":0.53333,"value":20.27}]},"foot2":{"rotate":[{"value":262.96},{"time":0.08815,"value":285.66},{"time":0.13222,"value":355.73},{"time":0.17629,"value":373.39},{"time":0.22037,"value":388.96},{"time":0.26667,"value":395.05},{"time":0.31171,"value":367.53},{"time":0.35259,"value":328.58},{"time":0.44073,"value":260.06},{"time":0.53333,"value":262.96}]},"forearm1":{"rotate":[{"value":27.41},{"time":0.04407,"value":21.50},{"time":0.08815,"value":16.71},{"time":0.13222,"value":30.62},{"time":0.31171,"value":38.33},{"time":0.35259,"value":37.81},{"time":0.39666,"value":16.47},{"time":0.44073,"value":17.71},{"time":0.53333,"value":27.41}]},"forearm2":{"rotate":[{"value":35.90},{"time":0.08815,"value":25.71},{"time":0.17629,"value":29.30},{"time":0.22037,"value":34.63,"curve":[0.24320,34.63,0.28888,38.95]},{"time":0.31171,"value":38.95},{"time":0.44073,"value":30.10},{"time":0.53333,"value":35.90}]},"hand1":{"rotate":[{"value":-20.20},{"time":0.04407,"value":-24.83},{"time":0.17629,"value":-14.29},{"time":0.35259,"value":21.85},{"time":0.39666,"value":9.46},{"time":0.44073,"value":12.08},{"time":0.53333,"value":-20.20}]},"hand2":{"rotate":[{"value":8.06},{"time":0.04407,"value":12.46},{"time":0.17629,"value":33.85},{"time":0.44073,"value":22.92},{"time":0.53333,"value":8.06}]},"head":{"rotate":[{"value":8.09},{"time":0.04407,"value":1.34,"curve":[0.07713,1.34,0.15665,5.50]},{"time":0.17629,"value":6.46},{"time":0.26667,"value":10.37},{"time":0.31171,"value":3.57,"curve":[0.34397,3.57,0.42047,6.86]},{"time":0.44073,"value":7.82},{"time":0.53333,"value":8.09}],"translate":[{"x":2.88,"y":0.23959},{"time":0.04407,"x":-3.51,"y":-1.82},{"time":0.17629,"x":4.61,"y":0.76121},{"time":0.26667,"x":1.55,"y":-6.16},{"time":0.31171,"x":-7.08,"y":-8.67},{"time":0.44073,"x":7.04,"y":0.05427},{"time":0.53333,"x":2.88,"y":0.23959}]},"hip":{"translate":[{"y":-8.40},{"time":0.04407,"x":1.64,"y":-12.88},{"time":0.08815,"x":1.64,"y":-11.23,"curve":[0.11018,1.64,0.15426,1.64,0.11018,-11.23,0.15426,8.97]},{"time":0.17629,"x":1.64,"y":8.97},{"time":0.22037,"x":1.64,"y":-1.10},{"time":0.26667,"y":-8.40},{"time":0.31171,"y":-10.18},{"time":0.35259,"y":-9.46,"curve":[0.37462,0,0.41870,0,0.37462,-9.46,0.41870,5.78]},{"time":0.44073,"y":5.78},{"time":0.48481,"x":1.64,"y":-1.10},{"time":0.53333,"y":-8.40}]},"mantles":{"rotate":[{},{"time":0.04407,"value":-2.18},{"time":0.26667,"value":2.90},{"time":0.31171,"value":-0.95251},{"time":0.53333}],"translate":[{},{"time":0.04407,"x":-2.60,"y":-0.65117},{"time":0.26667,"x":1.40,"y":-0.59287},{"time":0.31171,"x":-2.60,"y":-0.65117},{"time":0.53333}]},"shin1":{"rotate":[{"value":-35.54},{"time":0.03333,"value":-75.65},{"time":0.06667,"value":-100.25},{"time":0.10000,"value":-83.77},{"time":0.13222,"value":-49.65},{"time":0.17629,"value":-75.41},{"time":0.20963,"value":-107.13},{"time":0.26667,"value":-105.73},{"time":0.30000,"value":-114.01},{"time":0.33055,"value":-106.93},{"time":0.35259,"value":-106.79},{"time":0.39666,"value":-86.44},{"time":0.43333,"value":-77.26},{"time":0.48481,"value":-44.49},{"time":0.53333,"value":-35.54}]},"shin2":{"rotate":[{"value":-58.66},{"time":0.03333,"value":-86.40},{"time":0.06667,"value":-110.66},{"time":0.10000,"value":-96.65},{"time":0.13222,"value":-66.33},{"time":0.17629,"value":-69.35},{"time":0.20963,"value":-66.46},{"time":0.26667,"value":-37.31},{"time":0.30000,"value":-64.68},{"time":0.33055,"value":-53.81},{"time":0.35259,"value":-21.76},{"time":0.39666,"value":7.56},{"time":0.43333,"value":-39.79},{"time":0.48481,"value":-43.23},{"time":0.53333,"value":-58.66}]},"thigh1":{"rotate":[{"value":62.14},{"time":0.03333,"value":78.08},{"time":0.06667,"value":62.27},{"time":0.10000,"value":28.04},{"time":0.13222,"value":11.88},{"time":0.17629,"value":6.85},{"time":0.20963,"value":13.55},{"time":0.26667,"value":10.34},{"time":0.30000,"value":42.43},{"time":0.33055,"value":65.81},{"time":0.35259,"value":74.84},{"time":0.39666,"value":63.94},{"time":0.43333,"value":80.86},{"time":0.48481,"value":68.70},{"time":0.53333,"value":62.14}],"translate":[{"x":6.03},{"time":0.13222,"x":-3.58,"y":1.43},{"time":0.17629,"x":0.23938,"y":2.72},{"time":0.26667,"x":6.14,"y":-0.59200},{"time":0.33055,"x":8.82,"y":5.78},{"time":0.39666,"x":31.00,"y":0.35998},{"time":0.48481,"x":22.13,"y":0.17999},{"time":0.53333,"x":6.03}]},"thigh2":{"rotate":[{"value":-46.44},{"time":0.03333,"value":-28.79},{"time":0.06667,"value":13.65},{"time":0.10000,"value":47.84},{"time":0.13222,"value":47.34},{"time":0.17629,"value":57.73},{"time":0.20963,"value":58.30},{"time":0.26667,"value":37.30},{"time":0.30000,"value":24.57},{"time":0.33055,"value":-2.07},{"time":0.35259,"value":-28.22},{"time":0.39666,"value":-42.23},{"time":0.43333,"value":-47.24},{"time":0.48481,"value":-53.45},{"time":0.53333,"value":-46.44}],"translate":[{"x":-8.32,"y":-2.38},{"time":0.13222,"x":-3.93,"y":-2.38},{"time":0.26667,"x":3.23,"y":-1.53},{"time":0.35259,"x":-18.12,"y":0.17599},{"time":0.39666,"x":-28.39,"y":0.17599},{"time":0.53333,"x":-8.32,"y":-2.38}]},"upperarm1":{"rotate":[{"value":-40.45},{"time":0.04407,"value":-34.97},{"time":0.08815,"value":1.80},{"time":0.13222,"value":42.59},{"time":0.31171,"value":77.45},{"time":0.35259,"value":48.22},{"time":0.39666,"value":26.18},{"time":0.44073,"value":-22.81},{"time":0.53333,"value":-40.45}],"translate":[{},{"time":0.04407,"x":1.34,"y":0.56706},{"time":0.17629,"x":-2.75,"y":-5.59},{"time":0.31171,"x":-3.11,"y":-2.46},{"time":0.44073,"x":-0.75191,"y":4.05},{"time":0.53333}]},"upperarm2":{"rotate":[{"value":30.80},{"time":0.04407,"value":38.30},{"time":0.13222,"value":5.43},{"time":0.22037,"value":-25.39,"curve":[0.24320,-25.39,0.28888,-31.62]},{"time":0.31171,"value":-31.62},{"time":0.44073,"value":21.28},{"time":0.53333,"value":30.80}],"translate":[{"x":-5.34,"y":-1.56},{"time":0.17629,"x":-6.44,"y":2.12},{"time":0.53333,"x":-5.34,"y":-1.56}]}},"events":[{"time":0.26667,"name":"footstep","string":""},{"time":0.53333,"name":"footstep","string":""}]},"walk":{"bones":{"body":{"rotate":[{"value":2.18},{"time":0.13333,"value":-2.56,"curve":[0.22628,-2.56,0.28333,4.74]},{"time":0.33333,"value":4.74},{"time":0.53333,"value":0.29797},{"time":0.66667,"value":-2.56,"curve":[0.75961,-2.56,0.81667,3.59]},{"time":0.86667,"value":3.59},{"time":1.07,"value":2.18}],"translate":[{"x":10.86,"y":-1.14},{"time":0.13333,"x":10.49,"y":-2.93},{"time":0.33333,"x":1.79,"y":5.09},{"time":0.53333,"x":12.04,"y":-2.64},{"time":0.66667,"x":10.49,"y":-2.93},{"time":0.86667,"x":1.79,"y":6.43},{"time":1.07,"x":10.86,"y":-1.14}]},"foot1":{"rotate":[{"value":17.40},{"time":0.13333,"value":-0.28435},{"time":0.40000,"value":-10.64},{"time":0.53333,"value":-8.72},{"time":0.66667,"value":-24.71},{"time":0.80000,"value":-43.25},{"time":0.93333,"value":-35.21},{"time":1.07,"value":17.40}]},"foot2":{"rotate":[{"value":-20.00},{"time":0.13333,"value":-36.59},{"time":0.26667,"value":-69.51},{"time":0.40000,"value":-13.92},{"time":0.53333,"value":33.26},{"time":0.66667,"value":0.41254},{"time":0.93333,"value":-1.16},{"time":1.07,"value":-20.00}]},"forearm1":{"rotate":[{"value":-11.70},{"time":0.13333,"value":-5.74},{"time":0.53333,"value":24.76},{"time":0.66667,"value":33.27,"curve":[0.70000,33.27,0.76667,3.09]},{"time":0.80000,"value":3.09},{"time":0.93333,"value":5.39},{"time":1.07,"value":-11.70}]},"forearm2":{"rotate":[{"value":21.05},{"time":0.13333,"value":24.41},{"time":0.26667,"value":-0.81017},{"time":0.40000,"value":23.68},{"time":0.53333,"value":23.62},{"time":0.66667,"value":25.56},{"time":0.80000,"value":12.56},{"time":0.93333,"value":-0.27057},{"time":1.07,"value":21.05}]},"hand1":{"rotate":[{"value":-19.63},{"time":0.13333,"value":-25.07},{"time":0.26667,"value":-27.67},{"time":0.40000,"value":-34.31},{"time":0.53333,"value":-24.05},{"time":0.80000,"value":16.76},{"time":0.93333,"value":7.44},{"time":1.07,"value":-19.63}]},"hand2":{"rotate":[{"value":-12.11},{"time":0.13333,"value":-8.88},{"time":0.26667,"value":13.76},{"time":0.40000,"value":-3.02},{"time":0.53333,"value":11.48},{"time":0.66667,"value":5.24},{"time":0.80000,"value":3.93},{"time":0.93333,"value":0.31298},{"time":1.07,"value":-12.11}]},"head":{"rotate":[{"value":-11.71},{"time":0.13333,"value":-2.88},{"time":0.33333,"value":-10.46},{"time":0.53333,"value":-6.47},{"time":0.66667,"value":-2.86},{"time":0.86667,"value":-8.52},{"time":1.07,"value":-11.71}],"translate":[{},{"time":0.13333,"x":-2.96,"y":-3.43},{"time":0.33333,"x":1.05,"y":0.33076},{"time":0.53333},{"time":0.66667,"x":-2.96,"y":-3.43},{"time":0.86667,"x":1.05,"y":0.33076},{"time":1.07}]},"hip":{"translate":[{"y":-7.40},{"time":0.13333,"y":-6.33},{"time":0.26667,"y":-1.45},{"time":0.33333,"y":1.49},{"time":0.40000,"y":0.87201},{"time":0.53333,"y":-9.60},{"time":0.66667,"y":-8.45},{"time":0.80000,"y":-1.45},{"time":0.86667,"y":1.49},{"time":0.93333,"y":0.87201},{"time":1.07,"y":-7.40}]},"mantles":{"rotate":[{"value":-3.56},{"time":0.33333,"value":-8.55},{"time":0.53333,"value":-6.74},{"time":0.86667,"value":-8.55},{"time":1.07,"value":-3.56}],"translate":[{},{"time":0.13333,"x":-1.90,"y":-1.47},{"time":0.33333,"x":-0.66050,"y":-0.20228},{"time":0.66667,"x":-1.90,"y":-1.47},{"time":0.86667,"x":-0.66050,"y":-0.20228},{"time":1.07}]},"shin1":{"rotate":[{"value":-26.05},{"time":0.06667,"value":-45.26},{"time":0.13333,"value":-54.92},{"time":0.20000,"value":-54.89},{"time":0.26667,"value":-48.17},{"time":0.33333,"value":-27.52},{"time":0.40000,"value":-19.35},{"time":0.46667,"value":-44.16},{"time":0.53333,"value":-49.37},{"time":0.60000,"value":-50.23},{"time":0.66667,"value":-50.46},{"time":0.73333,"value":-60.15},{"time":0.80000,"value":-69.15},{"time":0.86667,"value":-88.23},{"time":0.93333,"value":-94.82},{"time":1,"value":-73.54},{"time":1.07,"value":-26.05}]},"shin2":{"rotate":[{"value":-21.25},{"time":0.06667,"value":-24.23},{"time":0.13333,"value":-25.92},{"time":0.20000,"value":-41.31},{"time":0.26667,"value":-54.44},{"time":0.33333,"value":-59.11},{"time":0.40000,"value":-65.08},{"time":0.46667,"value":-51.95},{"time":0.53333,"value":-21.13},{"time":0.60000,"value":-29.87},{"time":0.66667,"value":-34.45},{"time":0.73333,"value":-37.14},{"time":0.80000,"value":-25.80},{"time":0.86667,"value":7.56,"curve":"stepped"},{"time":0.93333,"value":7.56},{"time":1,"value":-20.35},{"time":1.07,"value":-21.25}]},"thigh1":{"rotate":[{"value":57.44},{"time":0.06667,"value":62.11},{"time":0.13333,"value":61.83},{"time":0.20000,"value":53.43},{"time":0.26667,"value":41.96},{"time":0.33333,"value":22.09},{"time":0.40000,"value":8.47},{"time":0.46667,"value":11.87},{"time":0.53333,"value":5.26},{"time":0.60000,"value":8.14},{"time":0.66667,"value":10.72},{"time":0.73333,"value":14.61},{"time":0.80000,"value":16.97},{"time":0.86667,"value":45.49},{"time":0.93333,"value":71.46},{"time":1,"value":72.21},{"time":1.07,"value":57.44}],"translate":[{"x":24.93},{"time":0.26667,"x":22.21},{"time":0.40000,"x":21.75,"y":-1.02},{"time":0.53333,"x":21.30},{"time":0.66667,"x":16.11,"y":1.01,"curve":[0.84700,16.11,0.86667,21.70,0.84700,1.01,0.86667,-3.93]},{"time":0.93333,"x":21.70,"y":-3.93},{"time":1.07,"x":24.93}]},"thigh2":{"rotate":[{"value":-21.05},{"time":0.06667,"value":-16.78},{"time":0.13333,"value":-13.04},{"time":0.20000,"value":-4.05},{"time":0.26667,"value":-4.14},{"time":0.33333,"value":11.84},{"time":0.40000,"value":29.11},{"time":0.46667,"value":36.62},{"time":0.53333,"value":34.14},{"time":0.60000,"value":32.79},{"time":0.66667,"value":29.44},{"time":0.73333,"value":18.49},{"time":0.80000,"value":1.76},{"time":0.86667,"value":-10.31},{"time":0.93333,"value":-7.92},{"time":1,"value":-8.19},{"time":1.07,"value":-21.05}],"translate":[{"x":-25.09},{"time":0.20000,"x":-35.18,"y":4.46,"curve":[0.31768,-35.18,0.35000,-9.43,0.31768,4.46,0.35000,-3.48]},{"time":0.40000,"x":-9.43,"y":-3.48},{"time":0.53333,"x":-4.25,"y":-1.42},{"time":0.66667,"x":-6.64,"y":0.04798},{"time":0.80000,"x":-11.55,"y":-2.12},{"time":0.93333,"x":-32.18,"y":-3.88},{"time":1.07,"x":-25.09}]},"upperarm1":{"rotate":[{"value":13.97},{"time":0.13333,"value":2.64},{"time":0.53333,"value":66.20},{"time":0.66667,"value":57.62},{"time":0.80000,"value":41.56},{"time":0.93333,"value":14.48},{"time":1.07,"value":13.97}],"translate":[{},{"time":0.13333,"x":4.42,"y":3.58},{"time":0.53333,"x":-0.22847,"y":-4.78},{"time":0.66667,"x":0.24763,"y":-2.40},{"time":1.07}]},"upperarm2":{"rotate":[{"value":349.66},{"time":0.13333,"value":349.79},{"time":0.26667,"value":343.54},{"time":0.40000,"value":334.09},{"time":0.53333,"value":327.79},{"time":0.80000,"value":338.54},{"time":0.93333,"value":354.69},{"time":1.07,"value":349.66}],"translate":[{},{"time":0.13333,"x":-0.76319,"y":-1.45},{"time":0.53333,"x":-0.19665,"y":8.70},{"time":1.07}]}},"events":[{"time":0.53333,"name":"footstep","string":""},{"time":1.07,"name":"footstep","string":""}]}}}